unitab/__init__.py
unitab-0.0.1.dev0.dist-info/METADATA
unitab-0.0.1.dev0.dist-info/WHEEL
unitab-0.0.1.dev0.dist-info/top_level.txt
unitab-0.0.1.dev0.dist-info/RECORD
