Metadata-Version: 2.1
Name: unitab
Version: 0.0.1.dev0
Summary: UniTAB - Unifying Text and Box Outputs for Grounded VL Modeling
Author: Fuheng Wu
Keywords: unitab
Classifier: Programming Language :: Python :: 3
Classifier: Programming Language :: Python :: 3.8
Classifier: Programming Language :: Python :: 3.9
Classifier: Programming Language :: Python :: 3.10
Requires-Dist: torch
